cq_enclosure/__init__.py
cq_enclosure/builders.py
cq_enclosure/enclosure.py
cq_enclosure/enclosure_parameters.py
cq_enclosure-0.1.0.dist-info/METADATA
cq_enclosure-0.1.0.dist-info/WHEEL
cq_enclosure-0.1.0.dist-info/top_level.txt
cq_enclosure-0.1.0.dist-info/RECORD
