Metadata-Version: 2.4
Name: cq-enclosure
Version: 0.1.0
Summary: Parametric IP66 enclosure generator for 3D printing
Requires-Python: >=3.10
Requires-Dist: cadquery>=2.5.2
Requires-Dist: pydantic>=2.10.5
Provides-Extra: build
Requires-Dist: setuptools; extra == "build"
